README.rst
setup.py
tidy_page.egg-info/PKG-INFO
tidy_page.egg-info/SOURCES.txt
tidy_page.egg-info/dependency_links.txt
tidy_page.egg-info/requires.txt
tidy_page.egg-info/top_level.txt
tidypage/__init__.py
tidypage/cleaners.py
tidypage/extractor.py
tidypage/titles.py